ctk_components/__init__.py
ctk_components/ctk_components.py
ctk_components/src/icons/arrow.png
ctk_components/src/icons/close_black.png
ctk_components/src/icons/close_white.png
ctk_components/src/icons/error.png
ctk_components/src/icons/eye1_black.png
ctk_components/src/icons/eye1_white.png
ctk_components/src/icons/eye2_black.png
ctk_components/src/icons/eye2_white.png
ctk_components/src/icons/icon.png
ctk_components/src/icons/image.png
ctk_components/src/icons/image1.jpg
ctk_components/src/icons/image2.jpg
ctk_components/src/icons/image3.jpg
ctk_components/src/icons/info.png
ctk_components/src/icons/left.png
ctk_components/src/icons/loader.gif
ctk_components/src/icons/right.png
ctk_components/src/icons/warning.png
ctk_components/src/icons/warning2.png
ctk_components/src/util/CTkGif.py
ctk_components/src/util/py_win_style.py
ctk_components/src/util/window_position.py
ctk_components-0.1.dist-info/METADATA
ctk_components-0.1.dist-info/WHEEL
ctk_components-0.1.dist-info/entry_points.txt
ctk_components-0.1.dist-info/top_level.txt
ctk_components-0.1.dist-info/RECORD
